perfectextractor_ui/__init__.py
perfectextractor_ui/admin.py
perfectextractor_ui/asgi.py
perfectextractor_ui/forms.py
perfectextractor_ui/models.py
perfectextractor_ui/settings.py
perfectextractor_ui/tasks.py
perfectextractor_ui/urls.py
perfectextractor_ui/views.py
perfectextractor_ui/wsgi.py
perfectextractor_ui/migrations/0001_initial.py
perfectextractor_ui/migrations/0002_corpus.py
perfectextractor_ui/migrations/__init__.py
perfectextractor_ui/static/css/bootstrap.min.css
perfectextractor_ui/static/css/bootstrap.min.css.map
perfectextractor_ui/static/js/base.js
perfectextractor_ui/templates/help.html
perfectextractor_ui/templates/home.html
perfectextractor_ui/templates/import.html
perfectextractor_ui/templates/progress.html
perfectextractor_ui/templates/base/base.html
perfectextractor_ui-0.1.8.dist-info/METADATA
perfectextractor_ui-0.1.8.dist-info/WHEEL
perfectextractor_ui-0.1.8.dist-info/top_level.txt
perfectextractor_ui-0.1.8.dist-info/RECORD
