Metadata-Version: 2.1
Name: perfectextractor-ui
Version: 0.1.8
Summary: A web frontend for perfectextractor
Home-page: https://github.com/time-in-translation/perfectextractor-ui
Author: Ben Bonfil
Author-email: bonfil@gmail.com
License: MIT
Classifier: Development Status :: 3 - Alpha
Classifier: License :: OSI Approved :: MIT License
Classifier: Programming Language :: Python :: 3
Classifier: Operating System :: OS Independent
Classifier: Topic :: Text Processing :: Linguistic
Requires-Python: >=3.6
Requires-Dist: django-widget-tweaks
Requires-Dist: perfectextractor
